{
  "result": [
    {
      "rule_id": "1",
      "description": "Cooking with Sheeps",
      "price_excl_vat": 50.00,
      "vat_rate": 6
    },
    {
      "rule_id": "2",
      "description": "Dancing with Sheeps",
      "price_excl_vat": 100.00,
      "vat_rate": 10
    },
    {
      "rule_id": "3",
      "description": "Partying with Sheeps",
      "price_excl_vat": 75.00,
      "vat_rate": 12
    },
    {
      "rule_id": "4",
      "description": "Hanging with Sheeps",
      "price_excl_vat":  25.00,
      "vat_rate": 10
    }
  ]
}